composure/__init__.py
composure/analyzer.py
composure/app.py
composure/cli.py
composure/puller.py
composure/scanner.py
composure-0.1.9.dist-info/licenses/LICENSE
composure-0.1.9.dist-info/METADATA
composure-0.1.9.dist-info/WHEEL
composure-0.1.9.dist-info/entry_points.txt
composure-0.1.9.dist-info/top_level.txt
composure-0.1.9.dist-info/RECORD
