Metadata-Version: 2.4
Name: composure
Version: 0.1.9
Summary: A terminal tool to audit, optimize, and visualize Docker-Compose stacks in real-time
Author-email: James Dimonaco <james@dimonaco.co.uk>
License: MIT
Project-URL: Homepage, https://github.com/JamesDimonaco/composure
Project-URL: Repository, https://github.com/JamesDimonaco/composure
Project-URL: Issues, https://github.com/JamesDimonaco/composure/issues
Keywords: docker,docker-compose,containers,devops,monitoring,tui,terminal,optimization
Classifier: Development Status :: 4 - Beta
Classifier: Environment :: Console
Classifier: Intended Audience :: Developers
Classifier: Intended Audience :: System Administrators
Classifier: License :: OSI Approved :: MIT License
Classifier: Operating System :: OS Independent
Classifier: Programming Language :: Python :: 3
Classifier: Programming Language :: Python :: 3.9
Classifier: Programming Language :: Python :: 3.10
Classifier: Programming Language :: Python :: 3.11
Classifier: Programming Language :: Python :: 3.12
Classifier: Topic :: System :: Monitoring
Classifier: Topic :: System :: Systems Administration
Classifier: Topic :: Utilities
Requires-Python: >=3.9
License-File: LICENSE
Requires-Dist: docker>=7.1.0
Requires-Dist: ruamel-yaml>=0.18.0
Requires-Dist: textual>=0.40.0
Requires-Dist: typer>=0.9.0
Dynamic: license-file
